protean_sqlalchemy/__init__.py
protean_sqlalchemy/__main__.py
protean_sqlalchemy/cli.py
protean_sqlalchemy/provider.py
protean_sqlalchemy/repository.py
protean_sqlalchemy/sa.py
protean_sqlalchemy-0.0.11.dist-info/AUTHORS.rst
protean_sqlalchemy-0.0.11.dist-info/LICENSE
protean_sqlalchemy-0.0.11.dist-info/METADATA
protean_sqlalchemy-0.0.11.dist-info/WHEEL
protean_sqlalchemy-0.0.11.dist-info/entry_points.txt
protean_sqlalchemy-0.0.11.dist-info/top_level.txt
protean_sqlalchemy-0.0.11.dist-info/RECORD
